workloadgen/__init__.py
workloadgen/data_preprocessing.py
workloadgen/evaluate.py
workloadgen/generate.py
workloadgen/train.py
workloadgen/vae_model.py
workloadgen-0.1.1.dist-info/licenses/LICENSE
workloadgen-0.1.1.dist-info/METADATA
workloadgen-0.1.1.dist-info/WHEEL
workloadgen-0.1.1.dist-info/entry_points.txt
workloadgen-0.1.1.dist-info/top_level.txt
workloadgen-0.1.1.dist-info/RECORD
