Metadata-Version: 2.4
Name: workloadgen
Version: 0.1.1
Summary: Synthetic SWF workload generation using Variational Autoencoders
Author: Your Name
License-File: LICENSE
Requires-Dist: torch
Requires-Dist: pandas
Requires-Dist: numpy
Requires-Dist: scikit-learn
Requires-Dist: matplotlib
Requires-Dist: seaborn
Dynamic: author
Dynamic: license-file
Dynamic: requires-dist
Dynamic: summary
